{
  "audit_event": "2016 Member Draw Reconciliation",
  "completion_date": "2026-03-18",
  "system_of_record": "workbench.db",
  "evidence_package": [
    {
      "filename": "walkthrough.md",
      "purpose": "Execution log and system upgrade summary",
      "status": "FINAL"
    },
    {
      "filename": "variance_report_2016.md",
      "purpose": "Detailed resolution of member draw discrepancies",
      "status": "FINAL"
    }
  ],
  "findings_summary": {
    "jz_variance_solved": true,
    "lg_variance_solved": true,
    "paralegal_recall": "100%"
  },
  "audit_trail_location": "/Volumes/batdrivetb5/AI_TRAINING/lawmodel1/data/rowboat-creative/RC-2026/audits/2016_reconciliation_ver_2026-03-18/"
}
